flask_rbac/__init__.py
flask_rbac/model.py
Flask_RBAC-0.5.0.dist-info/AUTHORS
Flask_RBAC-0.5.0.dist-info/LICENSE
Flask_RBAC-0.5.0.dist-info/METADATA
Flask_RBAC-0.5.0.dist-info/WHEEL
Flask_RBAC-0.5.0.dist-info/top_level.txt
Flask_RBAC-0.5.0.dist-info/RECORD
