Metadata-Version: 1.1
Name: Flask-RBAC
Version: 0.5.0
Summary: RBAC support for Flask
Home-page: https://github.com/shonenada/flask-rbac
Author: Yaoda Liu
Author-email: shonenada@gmail.com
License: UNKNOWN
Platform: any
Classifier: Framework :: Flask
Classifier: Environment :: Web Environment
Classifier: License :: OSI Approved :: MIT License
Classifier: Operating System :: OS Independent
Classifier: Programming Language :: Python
Classifier: Programming Language :: Python :: 3
Classifier: Development Status :: 3 - Alpha
Classifier: Intended Audience :: Developers
Classifier: Topic :: Internet :: WWW/HTTP :: Dynamic Content
